{
  "zones": [
    {
      "zone_id": 2,
      "current_aqi": 114,
      "pm25": null,
      "pm10": 34.33,
      "no2": 0.21,
      "o3": 80.92,
      "co": 122.26,
      "data_source": "api-ninjas",
      "last_updated": "2026-04-07T03:34:35.109Z"
    },
    {
      "zone_id": 3,
      "current_aqi": 114,
      "pm25": null,
      "pm10": 34.33,
      "no2": 0.21,
      "o3": 80.92,
      "co": 122.26,
      "data_source": "api-ninjas",
      "last_updated": "2026-04-07T03:34:35.456Z"
    },
    {
      "zone_id": 4,
      "current_aqi": 114,
      "pm25": null,
      "pm10": 34.33,
      "no2": 0.21,
      "o3": 80.92,
      "co": 122.26,
      "data_source": "api-ninjas",
      "last_updated": "2026-04-07T03:34:36.622Z"
    },
    {
      "zone_id": 20,
      "current_aqi": 114,
      "pm25": null,
      "pm10": 34.33,
      "no2": 0.21,
      "o3": 80.92,
      "co": 122.26,
      "data_source": "api-ninjas",
      "last_updated": "2026-04-07T03:34:36.637Z"
    },
    {
      "zone_id": 5,
      "current_aqi": 115,
      "pm25": null,
      "pm10": 35.18,
      "no2": 0.86,
      "o3": 81.14,
      "co": 128.43,
      "data_source": "api-ninjas",
      "last_updated": "2026-04-07T03:34:36.644Z"
    },
    {
      "zone_id": 6,
      "current_aqi": 114,
      "pm25": null,
      "pm10": 34.33,
      "no2": 0.21,
      "o3": 80.92,
      "co": 122.26,
      "data_source": "api-ninjas",
      "last_updated": "2026-04-07T03:34:39.266Z"
    },
    {
      "zone_id": 1,
      "current_aqi": 114,
      "pm25": null,
      "pm10": 34.1,
      "no2": 0.16,
      "o3": 80.94,
      "co": 121.66,
      "data_source": "api-ninjas",
      "last_updated": "2026-04-07T03:34:39.371Z"
    },
    {
      "zone_id": 7,
      "current_aqi": 114,
      "pm25": null,
      "pm10": 34.33,
      "no2": 0.21,
      "o3": 80.92,
      "co": 122.26,
      "data_source": "api-ninjas",
      "last_updated": "2026-04-07T03:34:39.360Z"
    },
    {
      "zone_id": 8,
      "current_aqi": 114,
      "pm25": null,
      "pm10": 34.33,
      "no2": 0.21,
      "o3": 80.92,
      "co": 122.26,
      "data_source": "api-ninjas",
      "last_updated": "2026-04-07T03:34:39.390Z"
    },
    {
      "zone_id": 9,
      "current_aqi": 114,
      "pm25": null,
      "pm10": 34.33,
      "no2": 0.21,
      "o3": 80.92,
      "co": 122.26,
      "data_source": "api-ninjas",
      "last_updated": "2026-04-07T03:34:39.258Z"
    },
    {
      "zone_id": 10,
      "current_aqi": 114,
      "pm25": null,
      "pm10": 34.33,
      "no2": 0.21,
      "o3": 80.92,
      "co": 122.26,
      "data_source": "api-ninjas",
      "last_updated": "2026-04-07T03:34:42.011Z"
    },
    {
      "zone_id": 11,
      "current_aqi": 114,
      "pm25": null,
      "pm10": 34.33,
      "no2": 0.21,
      "o3": 80.92,
      "co": 122.26,
      "data_source": "api-ninjas",
      "last_updated": "2026-04-07T03:34:42.017Z"
    },
    {
      "zone_id": 12,
      "current_aqi": 114,
      "pm25": null,
      "pm10": 34.1,
      "no2": 0.16,
      "o3": 80.94,
      "co": 121.66,
      "data_source": "api-ninjas",
      "last_updated": "2026-04-07T03:34:42.037Z"
    },
    {
      "zone_id": 13,
      "current_aqi": 114,
      "pm25": null,
      "pm10": 34.33,
      "no2": 0.21,
      "o3": 80.92,
      "co": 122.26,
      "data_source": "api-ninjas",
      "last_updated": "2026-04-07T03:34:42.031Z"
    },
    {
      "zone_id": 14,
      "current_aqi": 114,
      "pm25": null,
      "pm10": 34.33,
      "no2": 0.21,
      "o3": 80.92,
      "co": 122.26,
      "data_source": "api-ninjas",
      "last_updated": "2026-04-07T03:34:42.119Z"
    },
    {
      "zone_id": 15,
      "current_aqi": 114,
      "pm25": null,
      "pm10": 34.33,
      "no2": 0.21,
      "o3": 80.92,
      "co": 122.26,
      "data_source": "api-ninjas",
      "last_updated": "2026-04-07T03:34:44.731Z"
    },
    {
      "zone_id": 18,
      "current_aqi": 114,
      "pm25": null,
      "pm10": 34.33,
      "no2": 0.21,
      "o3": 80.92,
      "co": 122.26,
      "data_source": "api-ninjas",
      "last_updated": "2026-04-07T03:34:44.831Z"
    }
  ],
  "lastUpdated": "2026-04-07T03:34:44.831Z",
  "nextUpdate": "2026-04-08T03:34:44.831Z",
  "version": "1.0.0"
}