{
  "zones": [
    {
      "zone_id": 2,
      "current_aqi": 201,
      "pm25": null,
      "pm10": 74.81,
      "no2": 3.36,
      "o3": 118.72,
      "co": 246.95,
      "data_source": "api-ninjas",
      "last_updated": "2026-01-28T02:34:52.109Z"
    },
    {
      "zone_id": 3,
      "current_aqi": 201,
      "pm25": null,
      "pm10": 74.81,
      "no2": 3.36,
      "o3": 118.72,
      "co": 246.95,
      "data_source": "api-ninjas",
      "last_updated": "2026-01-28T02:34:51.089Z"
    },
    {
      "zone_id": 4,
      "current_aqi": 201,
      "pm25": null,
      "pm10": 74.81,
      "no2": 3.36,
      "o3": 118.72,
      "co": 246.95,
      "data_source": "api-ninjas",
      "last_updated": "2026-01-28T02:34:52.110Z"
    },
    {
      "zone_id": 20,
      "current_aqi": 201,
      "pm25": null,
      "pm10": 74.81,
      "no2": 3.36,
      "o3": 118.72,
      "co": 246.95,
      "data_source": "api-ninjas",
      "last_updated": "2026-01-28T02:34:52.083Z"
    },
    {
      "zone_id": 5,
      "current_aqi": 201,
      "pm25": null,
      "pm10": 81.29,
      "no2": 4.58,
      "o3": 117.95,
      "co": 267.33,
      "data_source": "api-ninjas",
      "last_updated": "2026-01-28T02:34:52.140Z"
    },
    {
      "zone_id": 6,
      "current_aqi": 201,
      "pm25": null,
      "pm10": 74.81,
      "no2": 3.36,
      "o3": 118.72,
      "co": 246.95,
      "data_source": "api-ninjas",
      "last_updated": "2026-01-28T02:34:54.714Z"
    },
    {
      "zone_id": 1,
      "current_aqi": 201,
      "pm25": null,
      "pm10": 73.82,
      "no2": 2.65,
      "o3": 118.25,
      "co": 239.78,
      "data_source": "api-ninjas",
      "last_updated": "2026-01-28T02:34:54.808Z"
    },
    {
      "zone_id": 7,
      "current_aqi": 201,
      "pm25": null,
      "pm10": 74.81,
      "no2": 3.36,
      "o3": 118.72,
      "co": 246.95,
      "data_source": "api-ninjas",
      "last_updated": "2026-01-28T02:34:54.683Z"
    },
    {
      "zone_id": 8,
      "current_aqi": 201,
      "pm25": null,
      "pm10": 74.81,
      "no2": 3.36,
      "o3": 118.72,
      "co": 246.95,
      "data_source": "api-ninjas",
      "last_updated": "2026-01-28T02:34:54.684Z"
    },
    {
      "zone_id": 9,
      "current_aqi": 201,
      "pm25": null,
      "pm10": 74.81,
      "no2": 3.36,
      "o3": 118.72,
      "co": 246.95,
      "data_source": "api-ninjas",
      "last_updated": "2026-01-28T02:34:54.720Z"
    },
    {
      "zone_id": 10,
      "current_aqi": 201,
      "pm25": null,
      "pm10": 74.81,
      "no2": 3.36,
      "o3": 118.72,
      "co": 246.95,
      "data_source": "api-ninjas",
      "last_updated": "2026-01-28T02:34:57.367Z"
    },
    {
      "zone_id": 11,
      "current_aqi": 201,
      "pm25": null,
      "pm10": 74.81,
      "no2": 3.36,
      "o3": 118.72,
      "co": 246.95,
      "data_source": "api-ninjas",
      "last_updated": "2026-01-28T02:34:57.375Z"
    },
    {
      "zone_id": 12,
      "current_aqi": 201,
      "pm25": null,
      "pm10": 73.82,
      "no2": 2.65,
      "o3": 118.25,
      "co": 239.78,
      "data_source": "api-ninjas",
      "last_updated": "2026-01-28T02:34:57.441Z"
    },
    {
      "zone_id": 13,
      "current_aqi": 201,
      "pm25": null,
      "pm10": 74.81,
      "no2": 3.36,
      "o3": 118.72,
      "co": 246.95,
      "data_source": "api-ninjas",
      "last_updated": "2026-01-28T02:34:57.383Z"
    },
    {
      "zone_id": 14,
      "current_aqi": 201,
      "pm25": null,
      "pm10": 74.81,
      "no2": 3.36,
      "o3": 118.72,
      "co": 246.95,
      "data_source": "api-ninjas",
      "last_updated": "2026-01-28T02:34:57.363Z"
    },
    {
      "zone_id": 15,
      "current_aqi": 201,
      "pm25": null,
      "pm10": 74.81,
      "no2": 3.36,
      "o3": 118.72,
      "co": 246.95,
      "data_source": "api-ninjas",
      "last_updated": "2026-01-28T02:35:00.084Z"
    },
    {
      "zone_id": 18,
      "current_aqi": 201,
      "pm25": null,
      "pm10": 74.81,
      "no2": 3.36,
      "o3": 118.72,
      "co": 246.95,
      "data_source": "api-ninjas",
      "last_updated": "2026-01-28T02:34:59.988Z"
    }
  ],
  "lastUpdated": "2026-01-28T02:35:00.084Z",
  "nextUpdate": "2026-01-29T02:35:00.084Z",
  "version": "1.0.0"
}