{
  "zones": [
    {
      "zone_id": 2,
      "current_aqi": 58,
      "pm25": null,
      "pm10": 71.92,
      "no2": 2.2,
      "o3": 50.3,
      "co": 143.69,
      "data_source": "api-ninjas",
      "last_updated": "2026-04-10T03:44:14.412Z"
    },
    {
      "zone_id": 3,
      "current_aqi": 58,
      "pm25": null,
      "pm10": 71.92,
      "no2": 2.2,
      "o3": 50.3,
      "co": 143.69,
      "data_source": "api-ninjas",
      "last_updated": "2026-04-10T03:44:15.799Z"
    },
    {
      "zone_id": 4,
      "current_aqi": 58,
      "pm25": null,
      "pm10": 71.92,
      "no2": 2.2,
      "o3": 50.3,
      "co": 143.69,
      "data_source": "api-ninjas",
      "last_updated": "2026-04-10T03:44:14.861Z"
    },
    {
      "zone_id": 20,
      "current_aqi": 58,
      "pm25": null,
      "pm10": 71.92,
      "no2": 2.2,
      "o3": 50.3,
      "co": 143.69,
      "data_source": "api-ninjas",
      "last_updated": "2026-04-10T03:44:15.877Z"
    },
    {
      "zone_id": 5,
      "current_aqi": 60,
      "pm25": null,
      "pm10": 74.78,
      "no2": 2.81,
      "o3": 50.73,
      "co": 150.44,
      "data_source": "api-ninjas",
      "last_updated": "2026-04-10T03:44:15.837Z"
    },
    {
      "zone_id": 6,
      "current_aqi": 58,
      "pm25": null,
      "pm10": 71.92,
      "no2": 2.2,
      "o3": 50.3,
      "co": 143.69,
      "data_source": "api-ninjas",
      "last_updated": "2026-04-10T03:44:18.503Z"
    },
    {
      "zone_id": 1,
      "current_aqi": 57,
      "pm25": null,
      "pm10": 69.61,
      "no2": 1.69,
      "o3": 50.96,
      "co": 137.52,
      "data_source": "api-ninjas",
      "last_updated": "2026-04-10T03:44:18.607Z"
    },
    {
      "zone_id": 7,
      "current_aqi": 58,
      "pm25": null,
      "pm10": 71.92,
      "no2": 2.2,
      "o3": 50.3,
      "co": 143.69,
      "data_source": "api-ninjas",
      "last_updated": "2026-04-10T03:44:18.599Z"
    },
    {
      "zone_id": 8,
      "current_aqi": 58,
      "pm25": null,
      "pm10": 71.92,
      "no2": 2.2,
      "o3": 50.3,
      "co": 143.69,
      "data_source": "api-ninjas",
      "last_updated": "2026-04-10T03:44:18.594Z"
    },
    {
      "zone_id": 9,
      "current_aqi": 58,
      "pm25": null,
      "pm10": 71.92,
      "no2": 2.2,
      "o3": 50.3,
      "co": 143.69,
      "data_source": "api-ninjas",
      "last_updated": "2026-04-10T03:44:18.511Z"
    },
    {
      "zone_id": 10,
      "current_aqi": 58,
      "pm25": null,
      "pm10": 71.92,
      "no2": 2.2,
      "o3": 50.3,
      "co": 143.69,
      "data_source": "api-ninjas",
      "last_updated": "2026-04-10T03:44:21.335Z"
    },
    {
      "zone_id": 11,
      "current_aqi": 58,
      "pm25": null,
      "pm10": 71.92,
      "no2": 2.2,
      "o3": 50.3,
      "co": 143.69,
      "data_source": "api-ninjas",
      "last_updated": "2026-04-10T03:44:21.314Z"
    },
    {
      "zone_id": 12,
      "current_aqi": 57,
      "pm25": null,
      "pm10": 69.61,
      "no2": 1.69,
      "o3": 50.96,
      "co": 137.52,
      "data_source": "api-ninjas",
      "last_updated": "2026-04-10T03:44:21.322Z"
    },
    {
      "zone_id": 13,
      "current_aqi": 58,
      "pm25": null,
      "pm10": 71.92,
      "no2": 2.2,
      "o3": 50.3,
      "co": 143.69,
      "data_source": "api-ninjas",
      "last_updated": "2026-04-10T03:44:21.228Z"
    },
    {
      "zone_id": 14,
      "current_aqi": 58,
      "pm25": null,
      "pm10": 71.92,
      "no2": 2.2,
      "o3": 50.3,
      "co": 143.69,
      "data_source": "api-ninjas",
      "last_updated": "2026-04-10T03:44:21.237Z"
    },
    {
      "zone_id": 15,
      "current_aqi": 58,
      "pm25": null,
      "pm10": 71.92,
      "no2": 2.2,
      "o3": 50.3,
      "co": 143.69,
      "data_source": "api-ninjas",
      "last_updated": "2026-04-10T03:44:24.055Z"
    },
    {
      "zone_id": 18,
      "current_aqi": 58,
      "pm25": null,
      "pm10": 71.92,
      "no2": 2.2,
      "o3": 50.3,
      "co": 143.69,
      "data_source": "api-ninjas",
      "last_updated": "2026-04-10T03:44:23.976Z"
    }
  ],
  "lastUpdated": "2026-04-10T03:44:24.055Z",
  "nextUpdate": "2026-04-11T03:44:24.055Z",
  "version": "1.0.0"
}